{
  "version": "2.0.0",
  "scrollSpeed": {
    "dsidediff": 1.6
  },
  "events": [
    {
      "t": 1650,
      "e": "FocusCamera",
      "v": {
	"char": 0
}
    },
    {
      "t": 2550,
      "e": "FocusCamera",
      "v": {
	"char": 1
}
    },
    {
      "t": 6450,
      "e": "FocusCamera",
      "v": {
	"char": 0
}
    },
    {
      "t": 9750,
      "e": "FocusCamera",
      "v": {
	"char": 1
}
    },
    {
      "t": 12149.9999999999,
      "e": "FocusCamera",
      "v": {
	"char": 0
}
    },
    {
      "t": 14699.9999999999,
      "e": "FocusCamera",
      "v": {
	"char": 1
}
    },
    {
      "t": 17099.9999999999,
      "e": "FocusCamera",
      "v": {
	"char": 0
}
    },
    {
      "t": 19349.9999999999,
      "e": "FocusCamera",
      "v": {
	"char": 1
}
    },
    {
      "t": 21749.9999999999,
      "e": "FocusCamera",
      "v": {
	"char": 0
}
    },
    {
      "t": 24149.9999999999,
      "e": "FocusCamera",
      "v": {
	"char": 1
}
    },
    {
      "t": 26549.9999999999,
      "e": "FocusCamera",
      "v": {
	"char": 0
}
    },
    {
      "t": 33450,
      "e": "FocusCamera",
      "v": {
	"char": 1
}
    },
    {
      "t": 35350,
      "e": "FocusCamera",
      "v": {
	"char": 0
}
    },
    {
      "t": 37150,
      "e": "FocusCamera",
      "v": {
	"char": 1
}
    },
    {
      "t": 38750,
      "e": "FocusCamera",
      "v": {
	"char": 0
}
    },
    {
      "t": 40350,
      "e": "FocusCamera",
      "v": {
	"char": 1
}
    },
    {
      "t": 41950,
      "e": "FocusCamera",
      "v": {
	"char": 0
}
    },
    {
      "t": 43350,
      "e": "FocusCamera",
      "v": {
	"char": 1
}
    },
    {
      "t": 44950,
      "e": "FocusCamera",
      "v": {
	"char": 0
}
    },
    {
      "t": 46550,
      "e": "FocusCamera",
      "v": {
	"char": 1
}
    },
    {
      "t": 49750,
      "e": "FocusCamera",
      "v": {
	"char": 0
}
    },
    {
      "t": 52950,
      "e": "FocusCamera",
      "v": {
	"char": 1
}
    },
    {
      "t": 56150,
      "e": "FocusCamera",
      "v": {
	"char": 0
}
    },
    {
      "t": 59650,
      "e": "FocusCamera",
      "v": {
	"char": 1
}
    },
    {
      "t": 61750,
      "e": "FocusCamera",
      "v": {
	"char": 0
}
    },
    {
      "t": 66550.0000000001,
      "e": "FocusCamera",
      "v": {
	"char": 1
}
    },
    {
      "t": 71350,
      "e": "FocusCamera",
      "v": {
	"char": 0
}
    },
    {
      "t": 73750,
      "e": "FocusCamera",
      "v": {
	"char": 1
}
    },
    {
      "t": 76150,
      "e": "FocusCamera",
      "v": {
	"char": 0
}
    },
    {
      "t": 80950,
      "e": "FocusCamera",
      "v": {
	"char": 1
}
    },
    {
      "t": 83350,
      "e": "FocusCamera",
      "v": {
	"char": 0
}
    },
    {
      "t": 88150,
      "e": "FocusCamera",
      "v": {
	"char": 1
}
    },
    {
      "t": 90150,
      "e": "FocusCamera",
      "v": {
	"char": 0
}
    },
    {
      "t": 92275,
      "e": "FocusCamera",
      "v": {
	"char": 1
}
    },
    {
      "t": 94150,
      "e": "FocusCamera",
      "v": {
	"char": 0
}
    },
    {
      "t": 95748.9473684211,
      "e": "ScrollSpeed",
      "v": {
	"duration": 4,
	"strumline": "both",
	"scroll": 1.5,
	"ease": "INSTANT",
	"absolute": false
}
    },
    {
      "t": 100150,
      "e": "FocusCamera",
      "v": {
	"char": 1
}
    },
    {
      "t": 101578.571428571,
      "e": "FocusCamera",
      "v": {
	"char": 0
}
    },
    {
      "t": 103007.142857143,
      "e": "FocusCamera",
      "v": {
	"char": 1
}
    },
    {
      "t": 104435.714285714,
      "e": "FocusCamera",
      "v": {
	"char": 0
}
    },
    {
      "t": 105864.285714286,
      "e": "FocusCamera",
      "v": {
	"char": 1
}
    },
    {
      "t": 107292.857142857,
      "e": "FocusCamera",
      "v": {
	"char": 0
}
    },
    {
      "t": 108721.428571429,
      "e": "FocusCamera",
      "v": {
	"char": 1
}
    },
    {
      "t": 110150,
      "e": "FocusCamera",
      "v": {
	"char": 0
}
    },
    {
      "t": 111578.571428571,
      "e": "FocusCamera",
      "v": {
	"char": 1
}
    },
    {
      "t": 114703.571428571,
      "e": "FocusCamera",
      "v": {
	"char": 0
}
    },
    {
      "t": 117292.857142857,
      "e": "FocusCamera",
      "v": {
	"char": 1
}
    },
    {
      "t": 118721.428571429,
      "e": "FocusCamera",
      "v": {
	"char": 0
}
    },
    {
      "t": 120507.142857143,
      "e": "FocusCamera",
      "v": {
	"char": 1
}
    },
    {
      "t": 121935.714285714,
      "e": "FocusCamera",
      "v": {
	"char": 0
}
    },
    {
      "t": 123007.142857143,
      "e": "FocusCamera",
      "v": {
	"char": 1
}
    },
    {
      "t": 125007.142857143,
      "e": "FocusCamera",
      "v": {
	"char": 0
}
    },
    {
      "t": 127007.142857143,
      "e": "FocusCamera",
      "v": {
	"char": 1
}
    },
    {
      "t": 129007.142857143,
      "e": "FocusCamera",
      "v": {
	"char": 0
}
    },
    {
      "t": 131007.142857143,
      "e": "FocusCamera",
      "v": {
	"char": 1
}
    },
    {
      "t": 133007.142857143,
      "e": "FocusCamera",
      "v": {
	"char": 0
}
    },
    {
      "t": 135007.142857143,
      "e": "FocusCamera",
      "v": {
	"char": 1
}
    },
    {
      "t": 137007.142857143,
      "e": "FocusCamera",
      "v": {
	"char": 0
}
    }
  ],
  "notes": {
    "dsidediff": [
      {
        "t": 1650,
        "d": 5,
        "l": 150,
        "k": "normal"
      },
      {
        "t": 1950,
        "d": 4,
        "l": 150,
        "k": "normal"
      },
      {
        "t": 2250,
        "d": 7,
        "l": 150,
        "k": "normal"
      },
      {
        "t": 2550,
        "d": 6,
        "l": 150,
        "k": "normal"
      },
      {
        "t": 2850,
        "d": 7,
        "l": 150,
        "k": "normal"
      },
      {
        "t": 3150,
        "d": 5,
        "l": 450,
        "k": "normal"
      },
      {
        "t": 3750,
        "d": 6,
        "l": 150,
        "k": "normal"
      },
      {
        "t": 4050,
        "d": 7,
        "l": 150,
        "k": "normal"
      },
      {
        "t": 4350,
        "d": 4,
        "l": 150,
        "k": "normal"
      },
      {
        "t": 4650,
        "d": 5,
        "l": 150,
        "k": "normal"
      },
      {
        "t": 4950,
        "d": 4,
        "l": 750,
        "k": "normal"
      },
      {
        "t": 6450,
        "d": 1,
        "l": 150,
        "k": "normal"
      },
      {
        "t": 6750,
        "d": 0,
        "l": 150,
        "k": "normal"
      },
      {
        "t": 7050,
        "d": 3,
        "l": 150,
        "k": "normal"
      },
      {
        "t": 7350,
        "d": 2,
        "l": 150,
        "k": "normal"
      },
      {
        "t": 7650,
        "d": 3,
        "l": 150,
        "k": "normal"
      },
      {
        "t": 7950,
        "d": 1,
        "l": 450,
        "k": "normal"
      },
      {
        "t": 8550,
        "d": 2,
        "l": 150,
        "k": "normal"
      },
      {
        "t": 8850,
        "d": 3,
        "l": 150,
        "k": "normal"
      },
      {
        "t": 9150,
        "d": 0,
        "l": 150,
        "k": "normal"
      },
      {
        "t": 9450,
        "d": 1,
        "l": 150,
        "k": "normal"
      },
      {
        "t": 9750,
        "d": 5,
        "l": 0,
        "k": "normal"
      },
      {
        "t": 9750,
        "d": 0,
        "l": 750,
        "k": "normal"
      },
      {
        "t": 10050,
        "d": 7,
        "l": 0,
        "k": "normal"
      },
      {
        "t": 10349.9999999999,
        "d": 7,
        "l": 0,
        "k": "normal"
      },
      {
        "t": 10649.9999999999,
        "d": 4,
        "l": 0,
        "k": "normal"
      },
      {
        "t": 10799.9999999999,
        "d": 4,
        "l": 0,
        "k": "normal"
      },
      {
        "t": 10949.9999999999,
        "d": 5,
        "l": 0,
        "k": "normal"
      },
      {
        "t": 11249.9999999999,
        "d": 7,
        "l": 0,
        "k": "normal"
      },
      {
        "t": 11549.9999999999,
        "d": 7,
        "l": 0,
        "k": "normal"
      },
      {
        "t": 11849.9999999999,
        "d": 4,
        "l": 0,
        "k": "normal"
      },
      {
        "t": 12149.9999999999,
        "d": 1,
        "l": 0,
        "k": "normal"
      },
      {
        "t": 12449.9999999999,
        "d": 3,
        "l": 0,
        "k": "normal"
      },
      {
        "t": 12749.9999999999,
        "d": 3,
        "l": 0,
        "k": "normal"
      },
      {
        "t": 13049.9999999999,
        "d": 0,
        "l": 0,
        "k": "normal"
      },
      {
        "t": 13199.9999999999,
        "d": 0,
        "l": 0,
        "k": "normal"
      },
      {
        "t": 13349.9999999999,
        "d": 1,
        "l": 0,
        "k": "normal"
      },
      {
        "t": 13649.9999999999,
        "d": 3,
        "l": 0,
        "k": "normal"
      },
      {
        "t": 13949.9999999999,
        "d": 3,
        "l": 0,
        "k": "normal"
      },
      {
        "t": 14249.9999999999,
        "d": 0,
        "l": 0,
        "k": "normal"
      },
      {
        "t": 14549.9999999999,
        "d": 5,
        "l": 0,
        "k": "normal"
      },
      {
        "t": 14699.9999999999,
        "d": 4,
        "l": 0,
        "k": "normal"
      },
      {
        "t": 14849.9999999999,
        "d": 6,
        "l": 0,
        "k": "normal"
      },
      {
        "t": 14999.9999999999,
        "d": 4,
        "l": 0,
        "k": "normal"
      },
      {
        "t": 15149.9999999999,
        "d": 6,
        "l": 0,
        "k": "normal"
      },
      {
        "t": 15449.9999999999,
        "d": 7,
        "l": 150,
        "k": "normal"
      },
      {
        "t": 15749.9999999999,
        "d": 6,
        "l": 0,
        "k": "normal"
      },
      {
        "t": 15899.9999999999,
        "d": 5,
        "l": 0,
        "k": "normal"
      },
      {
        "t": 16049.9999999999,
        "d": 4,
        "l": 150,
        "k": "normal"
      },
      {
        "t": 16349.9999999999,
        "d": 5,
        "l": 150,
        "k": "normal"
      },
      {
        "t": 16649.9999999999,
        "d": 7,
        "l": 150,
        "k": "normal"
      },
      {
        "t": 16949.9999999999,
        "d": 1,
        "l": 0,
        "k": "normal"
      },
      {
        "t": 17099.9999999999,
        "d": 0,
        "l": 0,
        "k": "normal"
      },
      {
        "t": 17249.9999999999,
        "d": 2,
        "l": 0,
        "k": "normal"
      },
      {
        "t": 17399.9999999999,
        "d": 0,
        "l": 0,
        "k": "normal"
      },
      {
        "t": 17549.9999999999,
        "d": 2,
        "l": 0,
        "k": "normal"
      },
      {
        "t": 17849.9999999999,
        "d": 3,
        "l": 150,
        "k": "normal"
      },
      {
        "t": 18149.9999999999,
        "d": 2,
        "l": 0,
        "k": "normal"
      },
      {
        "t": 18299.9999999999,
        "d": 1,
        "l": 0,
        "k": "normal"
      },
      {
        "t": 18449.9999999999,
        "d": 0,
        "l": 150,
        "k": "normal"
      },
      {
        "t": 18749.9999999999,
        "d": 1,
        "l": 150,
        "k": "normal"
      },
      {
        "t": 19049.9999999999,
        "d": 3,
        "l": 150,
        "k": "normal"
      },
      {
        "t": 19349.9999999999,
        "d": 5,
        "l": 0,
        "k": "normal"
      },
      {
        "t": 19649.9999999999,
        "d": 7,
        "l": 0,
        "k": "normal"
      },
      {
        "t": 19949.9999999999,
        "d": 7,
        "l": 0,
        "k": "normal"
      },
      {
        "t": 20249.9999999999,
        "d": 4,
        "l": 0,
        "k": "normal"
      },
      {
        "t": 20399.9999999999,
        "d": 5,
        "l": 0,
        "k": "normal"
      },
      {
        "t": 20549.9999999999,
        "d": 4,
        "l": 0,
        "k": "normal"
      },
      {
        "t": 20699.9999999999,
        "d": 7,
        "l": 150,
        "k": "normal"
      },
      {
        "t": 20999.9999999999,
        "d": 5,
        "l": 0,
        "k": "normal"
      },
      {
        "t": 21149.9999999999,
        "d": 6,
        "l": 450,
        "k": "normal"
      },
      {
        "t": 21149.9999999999,
        "d": 7,
        "l": 450,
        "k": "normal"
      },
      {
        "t": 21749.9999999999,
        "d": 1,
        "l": 0,
        "k": "normal"
      },
      {
        "t": 22049.9999999999,
        "d": 3,
        "l": 0,
        "k": "normal"
      },
      {
        "t": 22349.9999999999,
        "d": 3,
        "l": 0,
        "k": "normal"
      },
      {
        "t": 22649.9999999999,
        "d": 0,
        "l": 0,
        "k": "normal"
      },
      {
        "t": 22799.9999999999,
        "d": 1,
        "l": 0,
        "k": "normal"
      },
      {
        "t": 22949.9999999999,
        "d": 0,
        "l": 0,
        "k": "normal"
      },
      {
        "t": 23099.9999999999,
        "d": 3,
        "l": 150,
        "k": "normal"
      },
      {
        "t": 23399.9999999999,
        "d": 1,
        "l": 0,
        "k": "normal"
      },
      {
        "t": 23549.9999999999,
        "d": 2,
        "l": 450,
        "k": "normal"
      },
      {
        "t": 23549.9999999999,
        "d": 3,
        "l": 450,
        "k": "normal"
      },
      {
        "t": 24149.9999999999,
        "d": 5,
        "l": 0,
        "k": "normal"
      },
      {
        "t": 24299.9999999999,
        "d": 4,
        "l": 0,
        "k": "normal"
      },
      {
        "t": 24449.9999999999,
        "d": 6,
        "l": 150,
        "k": "normal"
      },
      {
        "t": 24749.9999999999,
        "d": 4,
        "l": 0,
        "k": "normal"
      },
      {
        "t": 24899.9999999999,
        "d": 5,
        "l": 0,
        "k": "normal"
      },
      {
        "t": 25049.9999999999,
        "d": 7,
        "l": 0,
        "k": "normal"
      },
      {
        "t": 25199.9999999999,
        "d": 5,
        "l": 0,
        "k": "normal"
      },
      {
        "t": 25349.9999999999,
        "d": 6,
        "l": 0,
        "k": "normal"
      },
      {
        "t": 25499.9999999999,
        "d": 4,
        "l": 150,
        "k": "normal"
      },
      {
        "t": 25799.9999999999,
        "d": 6,
        "l": 0,
        "k": "normal"
      },
      {
        "t": 25949.9999999999,
        "d": 7,
        "l": 450,
        "k": "normal"
      },
      {
        "t": 25949.9999999999,
        "d": 5,
        "l": 450,
        "k": "normal"
      },
      {
        "t": 26549.9999999999,
        "d": 1,
        "l": 0,
        "k": "normal"
      },
      {
        "t": 26699.9999999999,
        "d": 0,
        "l": 0,
        "k": "normal"
      },
      {
        "t": 26849.9999999999,
        "d": 2,
        "l": 150,
        "k": "normal"
      },
      {
        "t": 27149.9999999999,
        "d": 0,
        "l": 0,
        "k": "normal"
      },
      {
        "t": 27299.9999999999,
        "d": 1,
        "l": 0,
        "k": "normal"
      },
      {
        "t": 27449.9999999999,
        "d": 3,
        "l": 0,
        "k": "normal"
      },
      {
        "t": 27599.9999999999,
        "d": 1,
        "l": 0,
        "k": "normal"
      },
      {
        "t": 27749.9999999999,
        "d": 2,
        "l": 0,
        "k": "normal"
      },
      {
        "t": 27899.9999999999,
        "d": 0,
        "l": 150,
        "k": "normal"
      },
      {
        "t": 28199.9999999999,
        "d": 2,
        "l": 0,
        "k": "normal"
      },
      {
        "t": 28349.9999999999,
        "d": 3,
        "l": 450,
        "k": "normal"
      },
      {
        "t": 28349.9999999999,
        "d": 1,
        "l": 450,
        "k": "normal"
      },
      {
        "t": 33450,
        "d": 7,
        "l": 0,
        "k": "normal"
      },
      {
        "t": 33550,
        "d": 6,
        "l": 0,
        "k": "normal"
      },
      {
        "t": 33650,
        "d": 7,
        "l": 0,
        "k": "normal"
      },
      {
        "t": 33750,
        "d": 6,
        "l": 0,
        "k": "normal"
      },
      {
        "t": 33950,
        "d": 4,
        "l": 0,
        "k": "normal"
      },
      {
        "t": 34150,
        "d": 7,
        "l": 0,
        "k": "normal"
      },
      {
        "t": 34350,
        "d": 4,
        "l": 0,
        "k": "normal"
      },
      {
        "t": 34550,
        "d": 6,
        "l": 0,
        "k": "normal"
      },
      {
        "t": 34750,
        "d": 4,
        "l": 0,
        "k": "normal"
      },
      {
        "t": 34950,
        "d": 7,
        "l": 300,
        "k": "normal"
      },
      {
        "t": 34950,
        "d": 6,
        "l": 300,
        "k": "normal"
      },
      {
        "t": 35050,
        "d": 3,
        "l": 0,
        "k": "normal"
      },
      {
        "t": 35150,
        "d": 2,
        "l": 0,
        "k": "normal"
      },
      {
        "t": 35250,
        "d": 3,
        "l": 0,
        "k": "normal"
      },
      {
        "t": 35350,
        "d": 2,
        "l": 0,
        "k": "normal"
      },
      {
        "t": 35550,
        "d": 0,
        "l": 0,
        "k": "normal"
      },
      {
        "t": 35750,
        "d": 3,
        "l": 0,
        "k": "normal"
      },
      {
        "t": 35950,
        "d": 0,
        "l": 0,
        "k": "normal"
      },
      {
        "t": 36150,
        "d": 2,
        "l": 0,
        "k": "normal"
      },
      {
        "t": 36350,
        "d": 0,
        "l": 0,
        "k": "normal"
      },
      {
        "t": 36550,
        "d": 2,
        "l": 300,
        "k": "normal"
      },
      {
        "t": 36550,
        "d": 3,
        "l": 300,
        "k": "normal"
      },
      {
        "t": 36750,
        "d": 4,
        "l": 0,
        "k": "normal"
      },
      {
        "t": 36850,
        "d": 5,
        "l": 0,
        "k": "normal"
      },
      {
        "t": 36950,
        "d": 6,
        "l": 0,
        "k": "normal"
      },
      {
        "t": 37150,
        "d": 7,
        "l": 0,
        "k": "normal"
      },
      {
        "t": 37350,
        "d": 5,
        "l": 0,
        "k": "normal"
      },
      {
        "t": 37550,
        "d": 4,
        "l": 0,
        "k": "normal"
      },
      {
        "t": 37650,
        "d": 5,
        "l": 0,
        "k": "normal"
      },
      {
        "t": 37750,
        "d": 6,
        "l": 0,
        "k": "normal"
      },
      {
        "t": 37950,
        "d": 7,
        "l": 0,
        "k": "normal"
      },
      {
        "t": 38050,
        "d": 5,
        "l": 0,
        "k": "normal"
      },
      {
        "t": 38150,
        "d": 4,
        "l": 300,
        "k": "normal"
      },
      {
        "t": 38150,
        "d": 6,
        "l": 300,
        "k": "normal"
      },
      {
        "t": 38350,
        "d": 0,
        "l": 0,
        "k": "normal"
      },
      {
        "t": 38450,
        "d": 1,
        "l": 0,
        "k": "normal"
      },
      {
        "t": 38550,
        "d": 2,
        "l": 0,
        "k": "normal"
      },
      {
        "t": 38750,
        "d": 3,
        "l": 0,
        "k": "normal"
      },
      {
        "t": 38950,
        "d": 1,
        "l": 0,
        "k": "normal"
      },
      {
        "t": 39150,
        "d": 0,
        "l": 0,
        "k": "normal"
      },
      {
        "t": 39250,
        "d": 1,
        "l": 0,
        "k": "normal"
      },
      {
        "t": 39350,
        "d": 2,
        "l": 0,
        "k": "normal"
      },
      {
        "t": 39550,
        "d": 3,
        "l": 0,
        "k": "normal"
      },
      {
        "t": 39650,
        "d": 1,
        "l": 0,
        "k": "normal"
      },
      {
        "t": 39750,
        "d": 0,
        "l": 300,
        "k": "normal"
      },
      {
        "t": 39750,
        "d": 2,
        "l": 300,
        "k": "normal"
      },
      {
        "t": 40050,
        "d": 4,
        "l": 0,
        "k": "normal"
      },
      {
        "t": 40150,
        "d": 7,
        "l": 0,
        "k": "normal"
      },
      {
        "t": 40350,
        "d": 4,
        "l": 0,
        "k": "normal"
      },
      {
        "t": 40450,
        "d": 4,
        "l": 0,
        "k": "normal"
      },
      {
        "t": 40550,
        "d": 7,
        "l": 0,
        "k": "normal"
      },
      {
        "t": 40750,
        "d": 4,
        "l": 0,
        "k": "normal"
      },
      {
        "t": 40850,
        "d": 4,
        "l": 0,
        "k": "normal"
      },
      {
        "t": 40950,
        "d": 7,
        "l": 0,
        "k": "normal"
      },
      {
        "t": 41150,
        "d": 6,
        "l": 0,
        "k": "normal"
      },
      {
        "t": 41350,
        "d": 5,
        "l": 0,
        "k": "normal"
      },
      {
        "t": 41350,
        "d": 7,
        "l": 0,
        "k": "normal"
      },
      {
        "t": 41550,
        "d": 4,
        "l": 0,
        "k": "normal"
      },
      {
        "t": 41650,
        "d": 0,
        "l": 0,
        "k": "normal"
      },
      {
        "t": 41750,
        "d": 3,
        "l": 0,
        "k": "normal"
      },
      {
        "t": 41950,
        "d": 0,
        "l": 0,
        "k": "normal"
      },
      {
        "t": 42050,
        "d": 0,
        "l": 0,
        "k": "normal"
      },
      {
        "t": 42150,
        "d": 3,
        "l": 0,
        "k": "normal"
      },
      {
        "t": 42350,
        "d": 0,
        "l": 0,
        "k": "normal"
      },
      {
        "t": 42450,
        "d": 0,
        "l": 0,
        "k": "normal"
      },
      {
        "t": 42550,
        "d": 3,
        "l": 0,
        "k": "normal"
      },
      {
        "t": 42750,
        "d": 2,
        "l": 0,
        "k": "normal"
      },
      {
        "t": 42950,
        "d": 1,
        "l": 0,
        "k": "normal"
      },
      {
        "t": 42950,
        "d": 3,
        "l": 0,
        "k": "normal"
      },
      {
        "t": 43150,
        "d": 0,
        "l": 0,
        "k": "normal"
      },
      {
        "t": 43150,
        "d": 7,
        "l": 0,
        "k": "normal"
      },
      {
        "t": 43350,
        "d": 6,
        "l": 300,
        "k": "normal"
      },
      {
        "t": 43750,
        "d": 5,
        "l": 300,
        "k": "normal"
      },
      {
        "t": 44150,
        "d": 7,
        "l": 300,
        "k": "normal"
      },
      {
        "t": 44550,
        "d": 4,
        "l": 300,
        "k": "normal"
      },
      {
        "t": 44750,
        "d": 3,
        "l": 0,
        "k": "normal"
      },
      {
        "t": 44950,
        "d": 2,
        "l": 300,
        "k": "normal"
      },
      {
        "t": 44950,
        "d": 6,
        "l": 200,
        "k": "normal"
      },
      {
        "t": 45250,
        "d": 4,
        "l": 200,
        "k": "normal"
      },
      {
        "t": 45350,
        "d": 1,
        "l": 300,
        "k": "normal"
      },
      {
        "t": 45550,
        "d": 5,
        "l": 100,
        "k": "normal"
      },
      {
        "t": 45750,
        "d": 7,
        "l": 700,
        "k": "normal"
      },
      {
        "t": 45750,
        "d": 3,
        "l": 300,
        "k": "normal"
      },
      {
        "t": 46150,
        "d": 0,
        "l": 300,
        "k": "normal"
      },
      {
        "t": 46550,
        "d": 2,
        "l": 200,
        "k": "normal"
      },
      {
        "t": 46550,
        "d": 6,
        "l": 500,
        "k": "normal"
      },
      {
        "t": 46850,
        "d": 0,
        "l": 200,
        "k": "normal"
      },
      {
        "t": 47150,
        "d": 1,
        "l": 100,
        "k": "normal"
      },
      {
        "t": 47150,
        "d": 4,
        "l": 500,
        "k": "normal"
      },
      {
        "t": 47350,
        "d": 3,
        "l": 700,
        "k": "normal"
      },
      {
        "t": 47750,
        "d": 4,
        "l": 300,
        "k": "normal"
      },
      {
        "t": 48150,
        "d": 7,
        "l": 0,
        "k": "normal"
      },
      {
        "t": 48350,
        "d": 6,
        "l": 0,
        "k": "normal"
      },
      {
        "t": 48550,
        "d": 5,
        "l": 0,
        "k": "normal"
      },
      {
        "t": 48950,
        "d": 4,
        "l": 0,
        "k": "normal"
      },
      {
        "t": 48950,
        "d": 6,
        "l": 0,
        "k": "normal"
      },
      {
        "t": 49150,
        "d": 5,
        "l": 0,
        "k": "normal"
      },
      {
        "t": 49350,
        "d": 7,
        "l": 0,
        "k": "normal"
      },
      {
        "t": 49350,
        "d": 4,
        "l": 0,
        "k": "normal"
      },
      {
        "t": 49550,
        "d": 5,
        "l": 0,
        "k": "normal"
      },
      {
        "t": 49750,
        "d": 5,
        "l": 0,
        "k": "normal"
      },
      {
        "t": 49750,
        "d": 2,
        "l": 500,
        "k": "normal"
      },
      {
        "t": 49950,
        "d": 4,
        "l": 900,
        "k": "normal"
      },
      {
        "t": 50350,
        "d": 0,
        "l": 500,
        "k": "normal"
      },
      {
        "t": 50950,
        "d": 0,
        "l": 300,
        "k": "normal"
      },
      {
        "t": 51350,
        "d": 3,
        "l": 0,
        "k": "normal"
      },
      {
        "t": 51550,
        "d": 2,
        "l": 0,
        "k": "normal"
      },
      {
        "t": 51750,
        "d": 1,
        "l": 0,
        "k": "normal"
      },
      {
        "t": 52150,
        "d": 0,
        "l": 0,
        "k": "normal"
      },
      {
        "t": 52150,
        "d": 2,
        "l": 0,
        "k": "normal"
      },
      {
        "t": 52350,
        "d": 1,
        "l": 0,
        "k": "normal"
      },
      {
        "t": 52550,
        "d": 3,
        "l": 0,
        "k": "normal"
      },
      {
        "t": 52550,
        "d": 0,
        "l": 0,
        "k": "normal"
      },
      {
        "t": 52750,
        "d": 1,
        "l": 0,
        "k": "normal"
      },
      {
        "t": 52950,
        "d": 1,
        "l": 0,
        "k": "normal"
      },
      {
        "t": 52950,
        "d": 6,
        "l": 500,
        "k": "normal"
      },
      {
        "t": 53150,
        "d": 0,
        "l": 900,
        "k": "normal"
      },
      {
        "t": 53550,
        "d": 7,
        "l": 500,
        "k": "normal"
      },
      {
        "t": 54150,
        "d": 6,
        "l": 0,
        "k": "normal"
      },
      {
        "t": 54350,
        "d": 4,
        "l": 0,
        "k": "normal"
      },
      {
        "t": 54550,
        "d": 5,
        "l": 0,
        "k": "normal"
      },
      {
        "t": 54550,
        "d": 4,
        "l": 0,
        "k": "normal"
      },
      {
        "t": 54750,
        "d": 6,
        "l": 0,
        "k": "normal"
      },
      {
        "t": 54750,
        "d": 4,
        "l": 0,
        "k": "normal"
      },
      {
        "t": 54950,
        "d": 7,
        "l": 300,
        "k": "normal"
      },
      {
        "t": 55350,
        "d": 5,
        "l": 0,
        "k": "normal"
      },
      {
        "t": 55350,
        "d": 4,
        "l": 0,
        "k": "normal"
      },
      {
        "t": 55550,
        "d": 4,
        "l": 0,
        "k": "normal"
      },
      {
        "t": 55750,
        "d": 5,
        "l": 0,
        "k": "normal"
      },
      {
        "t": 55850,
        "d": 6,
        "l": 0,
        "k": "normal"
      },
      {
        "t": 55950,
        "d": 7,
        "l": 0,
        "k": "normal"
      },
      {
        "t": 56150,
        "d": 4,
        "l": 700,
        "k": "normal"
      },
      {
        "t": 56150,
        "d": 2,
        "l": 500,
        "k": "normal"
      },
      {
        "t": 56750,
        "d": 3,
        "l": 500,
        "k": "normal"
      },
      {
        "t": 57350,
        "d": 2,
        "l": 0,
        "k": "normal"
      },
      {
        "t": 57550,
        "d": 0,
        "l": 0,
        "k": "normal"
      },
      {
        "t": 57750,
        "d": 1,
        "l": 0,
        "k": "normal"
      },
      {
        "t": 57750,
        "d": 0,
        "l": 0,
        "k": "normal"
      },
      {
        "t": 57950,
        "d": 2,
        "l": 0,
        "k": "normal"
      },
      {
        "t": 57950,
        "d": 0,
        "l": 0,
        "k": "normal"
      },
      {
        "t": 58150,
        "d": 3,
        "l": 300,
        "k": "normal"
      },
      {
        "t": 58550,
        "d": 1,
        "l": 0,
        "k": "normal"
      },
      {
        "t": 58550,
        "d": 0,
        "l": 0,
        "k": "normal"
      },
      {
        "t": 58750,
        "d": 0,
        "l": 0,
        "k": "normal"
      },
      {
        "t": 58950,
        "d": 1,
        "l": 0,
        "k": "normal"
      },
      {
        "t": 59050,
        "d": 2,
        "l": 0,
        "k": "normal"
      },
      {
        "t": 59150,
        "d": 3,
        "l": 0,
        "k": "normal"
      },
      {
        "t": 59350,
        "d": 0,
        "l": 750,
        "k": "normal"
      },
      {
        "t": 59650,
        "d": 4,
        "l": 0,
        "k": "normal"
      },
      {
        "t": 59950,
        "d": 6,
        "l": 0,
        "k": "normal"
      },
      {
        "t": 60250,
        "d": 7,
        "l": 0,
        "k": "normal"
      },
      {
        "t": 60400,
        "d": 6,
        "l": 0,
        "k": "normal"
      },
      {
        "t": 60550,
        "d": 5,
        "l": 450,
        "k": "normal"
      },
      {
        "t": 61450,
        "d": 0,
        "l": 0,
        "k": "normal"
      },
      {
        "t": 61750,
        "d": 2,
        "l": 0,
        "k": "normal"
      },
      {
        "t": 62050,
        "d": 3,
        "l": 0,
        "k": "normal"
      },
      {
        "t": 62200,
        "d": 2,
        "l": 0,
        "k": "normal"
      },
      {
        "t": 62350,
        "d": 1,
        "l": 450,
        "k": "normal"
      },
      {
        "t": 63250,
        "d": 5,
        "l": 0,
        "k": "normal"
      },
      {
        "t": 63400,
        "d": 4,
        "l": 0,
        "k": "normal"
      },
      {
        "t": 63550,
        "d": 7,
        "l": 0,
        "k": "normal"
      },
      {
        "t": 63700,
        "d": 4,
        "l": 0,
        "k": "normal"
      },
      {
        "t": 63850,
        "d": 6,
        "l": 450,
        "k": "normal"
      },
      {
        "t": 64450,
        "d": 4,
        "l": 150,
        "k": "normal"
      },
      {
        "t": 65050,
        "d": 1,
        "l": 0,
        "k": "normal"
      },
      {
        "t": 65200,
        "d": 0,
        "l": 0,
        "k": "normal"
      },
      {
        "t": 65350,
        "d": 3,
        "l": 0,
        "k": "normal"
      },
      {
        "t": 65500,
        "d": 0,
        "l": 0,
        "k": "normal"
      },
      {
        "t": 65650,
        "d": 2,
        "l": 450,
        "k": "normal"
      },
      {
        "t": 66250,
        "d": 0,
        "l": 150,
        "k": "normal"
      },
      {
        "t": 66550.0000000001,
        "d": 6,
        "l": 0,
        "k": "normal"
      },
      {
        "t": 66850,
        "d": 6,
        "l": 0,
        "k": "normal"
      },
      {
        "t": 67150,
        "d": 4,
        "l": 0,
        "k": "normal"
      },
      {
        "t": 67300,
        "d": 5,
        "l": 0,
        "k": "normal"
      },
      {
        "t": 67450,
        "d": 6,
        "l": 750,
        "k": "normal"
      },
      {
        "t": 68350,
        "d": 2,
        "l": 0,
        "k": "normal"
      },
      {
        "t": 68650,
        "d": 2,
        "l": 0,
        "k": "normal"
      },
      {
        "t": 68950,
        "d": 0,
        "l": 0,
        "k": "normal"
      },
      {
        "t": 69100,
        "d": 1,
        "l": 0,
        "k": "normal"
      },
      {
        "t": 69250,
        "d": 2,
        "l": 750,
        "k": "normal"
      },
      {
        "t": 69850,
        "d": 4,
        "l": 150,
        "k": "normal"
      },
      {
        "t": 70150,
        "d": 5,
        "l": 450,
        "k": "normal"
      },
      {
        "t": 70750,
        "d": 7,
        "l": 450,
        "k": "normal"
      },
      {
        "t": 71350,
        "d": 5,
        "l": 450,
        "k": "normal"
      },
      {
        "t": 71950,
        "d": 4,
        "l": 750,
        "k": "normal"
      },
      {
        "t": 71950,
        "d": 1,
        "l": 750,
        "k": "normal"
      },
      {
        "t": 72850,
        "d": 7,
        "l": 750,
        "k": "normal"
      },
      {
        "t": 72850,
        "d": 2,
        "l": 450,
        "k": "normal"
      },
      {
        "t": 73450,
        "d": 3,
        "l": 150,
        "k": "normal"
      },
      {
        "t": 73750,
        "d": 5,
        "l": 0,
        "k": "normal"
      },
      {
        "t": 74050,
        "d": 5,
        "l": 0,
        "k": "normal"
      },
      {
        "t": 74200,
        "d": 6,
        "l": 0,
        "k": "normal"
      },
      {
        "t": 74350,
        "d": 5,
        "l": 0,
        "k": "normal"
      },
      {
        "t": 74500,
        "d": 6,
        "l": 0,
        "k": "normal"
      },
      {
        "t": 74650,
        "d": 5,
        "l": 150,
        "k": "normal"
      },
      {
        "t": 74950,
        "d": 4,
        "l": 150,
        "k": "normal"
      },
      {
        "t": 75250,
        "d": 6,
        "l": 0,
        "k": "normal"
      },
      {
        "t": 75250,
        "d": 4,
        "l": 0,
        "k": "normal"
      },
      {
        "t": 75400,
        "d": 7,
        "l": 0,
        "k": "normal"
      },
      {
        "t": 75550,
        "d": 1,
        "l": 0,
        "k": "normal"
      },
      {
        "t": 75850,
        "d": 1,
        "l": 0,
        "k": "normal"
      },
      {
        "t": 76000,
        "d": 2,
        "l": 0,
        "k": "normal"
      },
      {
        "t": 76150,
        "d": 1,
        "l": 0,
        "k": "normal"
      },
      {
        "t": 76300,
        "d": 2,
        "l": 0,
        "k": "normal"
      },
      {
        "t": 76450,
        "d": 1,
        "l": 150,
        "k": "normal"
      },
      {
        "t": 76750,
        "d": 0,
        "l": 150,
        "k": "normal"
      },
      {
        "t": 77050,
        "d": 2,
        "l": 0,
        "k": "normal"
      },
      {
        "t": 77050,
        "d": 0,
        "l": 0,
        "k": "normal"
      },
      {
        "t": 77200,
        "d": 3,
        "l": 0,
        "k": "normal"
      },
      {
        "t": 77350,
        "d": 4,
        "l": 0,
        "k": "normal"
      },
      {
        "t": 77650,
        "d": 4,
        "l": 0,
        "k": "normal"
      },
      {
        "t": 77800,
        "d": 6,
        "l": 0,
        "k": "normal"
      },
      {
        "t": 77950,
        "d": 4,
        "l": 150,
        "k": "normal"
      },
      {
        "t": 78250,
        "d": 7,
        "l": 0,
        "k": "normal"
      },
      {
        "t": 78400,
        "d": 5,
        "l": 0,
        "k": "normal"
      },
      {
        "t": 78550,
        "d": 4,
        "l": 150,
        "k": "normal"
      },
      {
        "t": 78850,
        "d": 7,
        "l": 150,
        "k": "normal"
      },
      {
        "t": 78850,
        "d": 5,
        "l": 150,
        "k": "normal"
      },
      {
        "t": 79150,
        "d": 0,
        "l": 0,
        "k": "normal"
      },
      {
        "t": 79450,
        "d": 0,
        "l": 0,
        "k": "normal"
      },
      {
        "t": 79600,
        "d": 2,
        "l": 0,
        "k": "normal"
      },
      {
        "t": 79750,
        "d": 0,
        "l": 150,
        "k": "normal"
      },
      {
        "t": 80050,
        "d": 3,
        "l": 0,
        "k": "normal"
      },
      {
        "t": 80200,
        "d": 1,
        "l": 0,
        "k": "normal"
      },
      {
        "t": 80350,
        "d": 0,
        "l": 150,
        "k": "normal"
      },
      {
        "t": 80650,
        "d": 3,
        "l": 150,
        "k": "normal"
      },
      {
        "t": 80650,
        "d": 1,
        "l": 300,
        "k": "normal"
      },
      {
        "t": 80950,
        "d": 7,
        "l": 0,
        "k": "normal"
      },
      {
        "t": 81100,
        "d": 4,
        "l": 0,
        "k": "normal"
      },
      {
        "t": 81250,
        "d": 7,
        "l": 0,
        "k": "normal"
      },
      {
        "t": 81400,
        "d": 6,
        "l": 0,
        "k": "normal"
      },
      {
        "t": 81550,
        "d": 5,
        "l": 150,
        "k": "normal"
      },
      {
        "t": 81850,
        "d": 4,
        "l": 0,
        "k": "normal"
      },
      {
        "t": 82000,
        "d": 7,
        "l": 0,
        "k": "normal"
      },
      {
        "t": 82150,
        "d": 4,
        "l": 0,
        "k": "normal"
      },
      {
        "t": 82300,
        "d": 5,
        "l": 0,
        "k": "normal"
      },
      {
        "t": 82450,
        "d": 6,
        "l": 150,
        "k": "normal"
      },
      {
        "t": 82450,
        "d": 4,
        "l": 150,
        "k": "normal"
      },
      {
        "t": 82750,
        "d": 3,
        "l": 0,
        "k": "normal"
      },
      {
        "t": 82900,
        "d": 0,
        "l": 0,
        "k": "normal"
      },
      {
        "t": 83050,
        "d": 3,
        "l": 0,
        "k": "normal"
      },
      {
        "t": 83200,
        "d": 2,
        "l": 0,
        "k": "normal"
      },
      {
        "t": 83350,
        "d": 1,
        "l": 150,
        "k": "normal"
      },
      {
        "t": 83650,
        "d": 0,
        "l": 0,
        "k": "normal"
      },
      {
        "t": 83800,
        "d": 3,
        "l": 0,
        "k": "normal"
      },
      {
        "t": 83950,
        "d": 0,
        "l": 0,
        "k": "normal"
      },
      {
        "t": 84100,
        "d": 1,
        "l": 0,
        "k": "normal"
      },
      {
        "t": 84250,
        "d": 2,
        "l": 150,
        "k": "normal"
      },
      {
        "t": 84250,
        "d": 0,
        "l": 150,
        "k": "normal"
      },
      {
        "t": 84550,
        "d": 5,
        "l": 150,
        "k": "normal"
      },
      {
        "t": 84850,
        "d": 6,
        "l": 150,
        "k": "normal"
      },
      {
        "t": 85150,
        "d": 5,
        "l": 0,
        "k": "normal"
      },
      {
        "t": 85300,
        "d": 4,
        "l": 0,
        "k": "normal"
      },
      {
        "t": 85450,
        "d": 7,
        "l": 150,
        "k": "normal"
      },
      {
        "t": 85750,
        "d": 5,
        "l": 150,
        "k": "normal"
      },
      {
        "t": 86050,
        "d": 7,
        "l": 150,
        "k": "normal"
      },
      {
        "t": 86350,
        "d": 4,
        "l": 150,
        "k": "normal"
      },
      {
        "t": 86350,
        "d": 1,
        "l": 150,
        "k": "normal"
      },
      {
        "t": 86650,
        "d": 5,
        "l": 150,
        "k": "normal"
      },
      {
        "t": 86650,
        "d": 2,
        "l": 150,
        "k": "normal"
      },
      {
        "t": 86950,
        "d": 6,
        "l": 150,
        "k": "normal"
      },
      {
        "t": 86950,
        "d": 1,
        "l": 0,
        "k": "normal"
      },
      {
        "t": 87100,
        "d": 0,
        "l": 0,
        "k": "normal"
      },
      {
        "t": 87250,
        "d": 7,
        "l": 150,
        "k": "normal"
      },
      {
        "t": 87250,
        "d": 3,
        "l": 150,
        "k": "normal"
      },
      {
        "t": 87550,
        "d": 1,
        "l": 150,
        "k": "normal"
      },
      {
        "t": 87850,
        "d": 3,
        "l": 150,
        "k": "normal"
      },
      {
        "t": 88150,
        "d": 6,
        "l": 0,
        "k": "normal"
      },
      {
        "t": 88150,
        "d": 7,
        "l": 0,
        "k": "normal"
      },
      {
        "t": 88400,
        "d": 5,
        "l": 0,
        "k": "normal"
      },
      {
        "t": 88650,
        "d": 6,
        "l": 0,
        "k": "normal"
      },
      {
        "t": 88650,
        "d": 7,
        "l": 0,
        "k": "normal"
      },
      {
        "t": 88900,
        "d": 4,
        "l": 0,
        "k": "normal"
      },
      {
        "t": 89150,
        "d": 5,
        "l": 0,
        "k": "normal"
      },
      {
        "t": 89275,
        "d": 6,
        "l": 0,
        "k": "normal"
      },
      {
        "t": 89400,
        "d": 5,
        "l": 0,
        "k": "normal"
      },
      {
        "t": 89650,
        "d": 4,
        "l": 0,
        "k": "normal"
      },
      {
        "t": 89900,
        "d": 7,
        "l": 0,
        "k": "normal"
      },
      {
        "t": 89900,
        "d": 5,
        "l": 0,
        "k": "normal"
      },
      {
        "t": 90150,
        "d": 2,
        "l": 0,
        "k": "normal"
      },
      {
        "t": 90150,
        "d": 3,
        "l": 0,
        "k": "normal"
      },
      {
        "t": 90400,
        "d": 1,
        "l": 0,
        "k": "normal"
      },
      {
        "t": 90650,
        "d": 2,
        "l": 0,
        "k": "normal"
      },
      {
        "t": 90650,
        "d": 3,
        "l": 0,
        "k": "normal"
      },
      {
        "t": 90900,
        "d": 0,
        "l": 0,
        "k": "normal"
      },
      {
        "t": 91150,
        "d": 1,
        "l": 0,
        "k": "normal"
      },
      {
        "t": 91275,
        "d": 2,
        "l": 0,
        "k": "normal"
      },
      {
        "t": 91400,
        "d": 1,
        "l": 0,
        "k": "normal"
      },
      {
        "t": 91650,
        "d": 0,
        "l": 0,
        "k": "normal"
      },
      {
        "t": 91900,
        "d": 3,
        "l": 0,
        "k": "normal"
      },
      {
        "t": 91900,
        "d": 1,
        "l": 0,
        "k": "normal"
      },
      {
        "t": 92150,
        "d": 7,
        "l": 0,
        "k": "normal"
      },
      {
        "t": 92275,
        "d": 5,
        "l": 0,
        "k": "normal"
      },
      {
        "t": 92400,
        "d": 4,
        "l": 0,
        "k": "normal"
      },
      {
        "t": 92525,
        "d": 5,
        "l": 0,
        "k": "normal"
      },
      {
        "t": 92650,
        "d": 7,
        "l": 125,
        "k": "normal"
      },
      {
        "t": 92900,
        "d": 6,
        "l": 750,
        "k": "normal"
      },
      {
        "t": 93150,
        "d": 3,
        "l": 0,
        "k": "normal"
      },
      {
        "t": 93275,
        "d": 1,
        "l": 0,
        "k": "normal"
      },
      {
        "t": 93400,
        "d": 0,
        "l": 0,
        "k": "normal"
      },
      {
        "t": 93525,
        "d": 1,
        "l": 0,
        "k": "normal"
      },
      {
        "t": 93650,
        "d": 3,
        "l": 125,
        "k": "normal"
      },
      {
        "t": 93900,
        "d": 2,
        "l": 125,
        "k": "normal"
      },
      {
        "t": 93900,
        "d": 6,
        "l": 125,
        "k": "normal"
      },
      {
        "t": 94150,
        "d": 0,
        "l": 0,
        "k": "normal"
      },
      {
        "t": 94150,
        "d": 7,
        "l": 0,
        "k": "normal"
      },
      {
        "t": 94400,
        "d": 4,
        "l": 0,
        "k": "normal"
      },
      {
        "t": 94400,
        "d": 1,
        "l": 0,
        "k": "normal"
      },
      {
        "t": 94650,
        "d": 3,
        "l": 375,
        "k": "normal"
      },
      {
        "t": 94650,
        "d": 5,
        "l": 375,
        "k": "normal"
      },
      {
        "t": 95150,
        "d": 1,
        "l": 375,
        "k": "normal"
      },
      {
        "t": 95150,
        "d": 4,
        "l": 375,
        "k": "normal"
      },
      {
        "t": 95650,
        "d": 0,
        "l": 375,
        "k": "normal"
      },
      {
        "t": 95650,
        "d": 7,
        "l": 375,
        "k": "normal"
      },
      {
        "t": 99900,
        "d": 4,
        "l": 0,
        "k": "normal"
      },
      {
        "t": 100150,
        "d": 7,
        "l": 0,
        "k": "normal"
      },
      {
        "t": 100150,
        "d": 6,
        "l": 0,
        "k": "normal"
      },
      {
        "t": 100328.571428571,
        "d": 4,
        "l": 0,
        "k": "normal"
      },
      {
        "t": 100507.142857143,
        "d": 7,
        "l": 0,
        "k": "normal"
      },
      {
        "t": 100507.142857143,
        "d": 6,
        "l": 0,
        "k": "normal"
      },
      {
        "t": 100685.714285714,
        "d": 4,
        "l": 0,
        "k": "normal"
      },
      {
        "t": 100775,
        "d": 5,
        "l": 0,
        "k": "normal"
      },
      {
        "t": 100864.285714286,
        "d": 7,
        "l": 0,
        "k": "normal"
      },
      {
        "t": 100953.571428571,
        "d": 5,
        "l": 0,
        "k": "normal"
      },
      {
        "t": 101042.857142857,
        "d": 4,
        "l": 0,
        "k": "normal"
      },
      {
        "t": 101221.428571429,
        "d": 6,
        "l": 267.857142857143,
        "k": "normal"
      },
      {
        "t": 101221.428571429,
        "d": 7,
        "l": 267.857142857143,
        "k": "normal"
      },
      {
        "t": 101400,
        "d": 0,
        "l": 0,
        "k": "normal"
      },
      {
        "t": 101578.571428571,
        "d": 3,
        "l": 0,
        "k": "normal"
      },
      {
        "t": 101578.571428571,
        "d": 2,
        "l": 0,
        "k": "normal"
      },
      {
        "t": 101757.142857143,
        "d": 0,
        "l": 0,
        "k": "normal"
      },
      {
        "t": 101935.714285714,
        "d": 3,
        "l": 0,
        "k": "normal"
      },
      {
        "t": 101935.714285714,
        "d": 2,
        "l": 0,
        "k": "normal"
      },
      {
        "t": 102114.285714286,
        "d": 0,
        "l": 0,
        "k": "normal"
      },
      {
        "t": 102203.571428571,
        "d": 1,
        "l": 0,
        "k": "normal"
      },
      {
        "t": 102292.857142857,
        "d": 3,
        "l": 0,
        "k": "normal"
      },
      {
        "t": 102382.142857143,
        "d": 1,
        "l": 0,
        "k": "normal"
      },
      {
        "t": 102471.428571429,
        "d": 0,
        "l": 0,
        "k": "normal"
      },
      {
        "t": 102650,
        "d": 2,
        "l": 267.857142857143,
        "k": "normal"
      },
      {
        "t": 102650,
        "d": 3,
        "l": 267.857142857143,
        "k": "normal"
      },
      {
        "t": 102828.571428571,
        "d": 4,
        "l": 0,
        "k": "normal"
      },
      {
        "t": 102917.857142857,
        "d": 5,
        "l": 0,
        "k": "normal"
      },
      {
        "t": 103007.142857143,
        "d": 7,
        "l": 0,
        "k": "normal"
      },
      {
        "t": 103007.142857143,
        "d": 4,
        "l": 0,
        "k": "normal"
      },
      {
        "t": 103185.714285714,
        "d": 5,
        "l": 0,
        "k": "normal"
      },
      {
        "t": 103364.285714286,
        "d": 4,
        "l": 0,
        "k": "normal"
      },
      {
        "t": 103542.857142857,
        "d": 5,
        "l": 0,
        "k": "normal"
      },
      {
        "t": 103632.142857143,
        "d": 4,
        "l": 0,
        "k": "normal"
      },
      {
        "t": 103721.428571429,
        "d": 7,
        "l": 0,
        "k": "normal"
      },
      {
        "t": 103900,
        "d": 5,
        "l": 0,
        "k": "normal"
      },
      {
        "t": 103900,
        "d": 4,
        "l": 0,
        "k": "normal"
      },
      {
        "t": 104078.571428571,
        "d": 6,
        "l": 267.857142857143,
        "k": "normal"
      },
      {
        "t": 104257.142857143,
        "d": 0,
        "l": 0,
        "k": "normal"
      },
      {
        "t": 104346.428571429,
        "d": 1,
        "l": 0,
        "k": "normal"
      },
      {
        "t": 104435.714285714,
        "d": 3,
        "l": 0,
        "k": "normal"
      },
      {
        "t": 104435.714285714,
        "d": 0,
        "l": 0,
        "k": "normal"
      },
      {
        "t": 104614.285714286,
        "d": 1,
        "l": 0,
        "k": "normal"
      },
      {
        "t": 104792.857142857,
        "d": 0,
        "l": 0,
        "k": "normal"
      },
      {
        "t": 104971.428571429,
        "d": 1,
        "l": 0,
        "k": "normal"
      },
      {
        "t": 105060.714285714,
        "d": 0,
        "l": 0,
        "k": "normal"
      },
      {
        "t": 105150,
        "d": 3,
        "l": 0,
        "k": "normal"
      },
      {
        "t": 105328.571428571,
        "d": 1,
        "l": 0,
        "k": "normal"
      },
      {
        "t": 105328.571428571,
        "d": 0,
        "l": 0,
        "k": "normal"
      },
      {
        "t": 105507.142857143,
        "d": 2,
        "l": 267.857142857143,
        "k": "normal"
      },
      {
        "t": 105864.285714286,
        "d": 6,
        "l": 0,
        "k": "normal"
      },
      {
        "t": 105953.571428571,
        "d": 5,
        "l": 0,
        "k": "normal"
      },
      {
        "t": 106042.857142857,
        "d": 4,
        "l": 0,
        "k": "normal"
      },
      {
        "t": 106221.428571429,
        "d": 6,
        "l": 267.857142857143,
        "k": "normal"
      },
      {
        "t": 106578.571428571,
        "d": 7,
        "l": 0,
        "k": "normal"
      },
      {
        "t": 106667.857142857,
        "d": 5,
        "l": 0,
        "k": "normal"
      },
      {
        "t": 106757.142857143,
        "d": 4,
        "l": 0,
        "k": "normal"
      },
      {
        "t": 106935.714285714,
        "d": 7,
        "l": 0,
        "k": "normal"
      },
      {
        "t": 106935.714285714,
        "d": 4,
        "l": 0,
        "k": "normal"
      },
      {
        "t": 107114.285714286,
        "d": 4,
        "l": 0,
        "k": "normal"
      },
      {
        "t": 107203.571428571,
        "d": 5,
        "l": 0,
        "k": "normal"
      },
      {
        "t": 107292.857142857,
        "d": 7,
        "l": 625,
        "k": "normal"
      },
      {
        "t": 107292.857142857,
        "d": 2,
        "l": 0,
        "k": "normal"
      },
      {
        "t": 107382.142857143,
        "d": 1,
        "l": 0,
        "k": "normal"
      },
      {
        "t": 107471.428571429,
        "d": 0,
        "l": 0,
        "k": "normal"
      },
      {
        "t": 107650,
        "d": 2,
        "l": 267.857142857143,
        "k": "normal"
      },
      {
        "t": 108007.142857143,
        "d": 3,
        "l": 0,
        "k": "normal"
      },
      {
        "t": 108096.428571429,
        "d": 1,
        "l": 0,
        "k": "normal"
      },
      {
        "t": 108185.714285714,
        "d": 0,
        "l": 0,
        "k": "normal"
      },
      {
        "t": 108364.285714286,
        "d": 3,
        "l": 0,
        "k": "normal"
      },
      {
        "t": 108364.285714286,
        "d": 0,
        "l": 0,
        "k": "normal"
      },
      {
        "t": 108542.857142857,
        "d": 0,
        "l": 0,
        "k": "normal"
      },
      {
        "t": 108542.857142857,
        "d": 7,
        "l": 0,
        "k": "normal"
      },
      {
        "t": 108632.142857143,
        "d": 1,
        "l": 0,
        "k": "normal"
      },
      {
        "t": 108721.428571429,
        "d": 3,
        "l": 625,
        "k": "normal"
      },
      {
        "t": 108721.428571429,
        "d": 4,
        "l": 0,
        "k": "normal"
      },
      {
        "t": 108721.428571429,
        "d": 7,
        "l": 0,
        "k": "normal"
      },
      {
        "t": 108900,
        "d": 5,
        "l": 0,
        "k": "normal"
      },
      {
        "t": 109078.571428571,
        "d": 7,
        "l": 0,
        "k": "normal"
      },
      {
        "t": 109078.571428571,
        "d": 6,
        "l": 0,
        "k": "normal"
      },
      {
        "t": 109257.142857143,
        "d": 5,
        "l": 0,
        "k": "normal"
      },
      {
        "t": 109346.428571429,
        "d": 4,
        "l": 0,
        "k": "normal"
      },
      {
        "t": 109435.714285714,
        "d": 6,
        "l": 0,
        "k": "normal"
      },
      {
        "t": 109614.285714286,
        "d": 7,
        "l": 0,
        "k": "normal"
      },
      {
        "t": 109703.571428571,
        "d": 5,
        "l": 0,
        "k": "normal"
      },
      {
        "t": 109792.857142857,
        "d": 6,
        "l": 267.857142857143,
        "k": "normal"
      },
      {
        "t": 109971.428571429,
        "d": 3,
        "l": 0,
        "k": "normal"
      },
      {
        "t": 110150,
        "d": 0,
        "l": 0,
        "k": "normal"
      },
      {
        "t": 110150,
        "d": 3,
        "l": 0,
        "k": "normal"
      },
      {
        "t": 110328.571428571,
        "d": 1,
        "l": 0,
        "k": "normal"
      },
      {
        "t": 110507.142857143,
        "d": 3,
        "l": 0,
        "k": "normal"
      },
      {
        "t": 110507.142857143,
        "d": 2,
        "l": 0,
        "k": "normal"
      },
      {
        "t": 110685.714285714,
        "d": 1,
        "l": 0,
        "k": "normal"
      },
      {
        "t": 110775,
        "d": 0,
        "l": 0,
        "k": "normal"
      },
      {
        "t": 110864.285714286,
        "d": 2,
        "l": 0,
        "k": "normal"
      },
      {
        "t": 111042.857142857,
        "d": 3,
        "l": 0,
        "k": "normal"
      },
      {
        "t": 111132.142857143,
        "d": 1,
        "l": 0,
        "k": "normal"
      },
      {
        "t": 111221.428571429,
        "d": 2,
        "l": 267.857142857143,
        "k": "normal"
      },
      {
        "t": 111578.571428571,
        "d": 7,
        "l": 0,
        "k": "normal"
      },
      {
        "t": 111667.857142857,
        "d": 6,
        "l": 0,
        "k": "normal"
      },
      {
        "t": 111757.142857143,
        "d": 4,
        "l": 0,
        "k": "normal"
      },
      {
        "t": 111846.428571429,
        "d": 4,
        "l": 0,
        "k": "normal"
      },
      {
        "t": 111935.714285714,
        "d": 7,
        "l": 0,
        "k": "normal"
      },
      {
        "t": 111935.714285714,
        "d": 5,
        "l": 0,
        "k": "normal"
      },
      {
        "t": 112114.285714286,
        "d": 7,
        "l": 0,
        "k": "normal"
      },
      {
        "t": 112114.285714286,
        "d": 5,
        "l": 0,
        "k": "normal"
      },
      {
        "t": 112292.857142857,
        "d": 7,
        "l": 0,
        "k": "normal"
      },
      {
        "t": 112471.428571429,
        "d": 4,
        "l": 0,
        "k": "normal"
      },
      {
        "t": 112650,
        "d": 7,
        "l": 0,
        "k": "normal"
      },
      {
        "t": 112650,
        "d": 5,
        "l": 0,
        "k": "normal"
      },
      {
        "t": 112828.571428571,
        "d": 7,
        "l": 0,
        "k": "normal"
      },
      {
        "t": 112828.571428571,
        "d": 5,
        "l": 0,
        "k": "normal"
      },
      {
        "t": 113007.142857143,
        "d": 7,
        "l": 0,
        "k": "normal"
      },
      {
        "t": 113007.142857143,
        "d": 6,
        "l": 0,
        "k": "normal"
      },
      {
        "t": 113185.714285714,
        "d": 5,
        "l": 0,
        "k": "normal"
      },
      {
        "t": 113364.285714286,
        "d": 4,
        "l": 0,
        "k": "normal"
      },
      {
        "t": 113542.857142857,
        "d": 5,
        "l": 0,
        "k": "normal"
      },
      {
        "t": 113721.428571429,
        "d": 6,
        "l": 0,
        "k": "normal"
      },
      {
        "t": 113721.428571429,
        "d": 7,
        "l": 0,
        "k": "normal"
      },
      {
        "t": 113900,
        "d": 7,
        "l": 0,
        "k": "normal"
      },
      {
        "t": 114078.571428571,
        "d": 4,
        "l": 0,
        "k": "normal"
      },
      {
        "t": 114257.142857143,
        "d": 5,
        "l": 0,
        "k": "normal"
      },
      {
        "t": 114435.714285714,
        "d": 3,
        "l": 0,
        "k": "normal"
      },
      {
        "t": 114435.714285714,
        "d": 4,
        "l": 0,
        "k": "normal"
      },
      {
        "t": 114525,
        "d": 2,
        "l": 0,
        "k": "normal"
      },
      {
        "t": 114614.285714286,
        "d": 0,
        "l": 0,
        "k": "normal"
      },
      {
        "t": 114614.285714286,
        "d": 5,
        "l": 0,
        "k": "normal"
      },
      {
        "t": 114703.571428571,
        "d": 0,
        "l": 0,
        "k": "normal"
      },
      {
        "t": 114792.857142857,
        "d": 3,
        "l": 0,
        "k": "normal"
      },
      {
        "t": 114792.857142857,
        "d": 6,
        "l": 0,
        "k": "normal"
      },
      {
        "t": 114792.857142857,
        "d": 7,
        "l": 0,
        "k": "normal"
      },
      {
        "t": 114792.857142857,
        "d": 1,
        "l": 0,
        "k": "normal"
      },
      {
        "t": 114971.428571429,
        "d": 3,
        "l": 0,
        "k": "normal"
      },
      {
        "t": 114971.428571429,
        "d": 7,
        "l": 0,
        "k": "normal"
      },
      {
        "t": 114971.428571429,
        "d": 1,
        "l": 0,
        "k": "normal"
      },
      {
        "t": 115150,
        "d": 3,
        "l": 0,
        "k": "normal"
      },
      {
        "t": 115150,
        "d": 4,
        "l": 625,
        "k": "normal"
      },
      {
        "t": 115328.571428571,
        "d": 0,
        "l": 0,
        "k": "normal"
      },
      {
        "t": 115507.142857143,
        "d": 3,
        "l": 0,
        "k": "normal"
      },
      {
        "t": 115507.142857143,
        "d": 1,
        "l": 0,
        "k": "normal"
      },
      {
        "t": 115685.714285714,
        "d": 3,
        "l": 0,
        "k": "normal"
      },
      {
        "t": 115685.714285714,
        "d": 1,
        "l": 0,
        "k": "normal"
      },
      {
        "t": 115864.285714286,
        "d": 3,
        "l": 0,
        "k": "normal"
      },
      {
        "t": 115864.285714286,
        "d": 2,
        "l": 0,
        "k": "normal"
      },
      {
        "t": 116042.857142857,
        "d": 1,
        "l": 0,
        "k": "normal"
      },
      {
        "t": 116221.428571429,
        "d": 0,
        "l": 0,
        "k": "normal"
      },
      {
        "t": 116400,
        "d": 1,
        "l": 0,
        "k": "normal"
      },
      {
        "t": 116578.571428571,
        "d": 2,
        "l": 0,
        "k": "normal"
      },
      {
        "t": 116578.571428571,
        "d": 3,
        "l": 0,
        "k": "normal"
      },
      {
        "t": 116757.142857143,
        "d": 3,
        "l": 0,
        "k": "normal"
      },
      {
        "t": 116935.714285714,
        "d": 0,
        "l": 0,
        "k": "normal"
      },
      {
        "t": 117114.285714286,
        "d": 1,
        "l": 0,
        "k": "normal"
      },
      {
        "t": 117292.857142857,
        "d": 7,
        "l": 0,
        "k": "normal"
      },
      {
        "t": 117292.857142857,
        "d": 0,
        "l": 0,
        "k": "normal"
      },
      {
        "t": 117471.428571429,
        "d": 4,
        "l": 0,
        "k": "normal"
      },
      {
        "t": 117471.428571429,
        "d": 1,
        "l": 0,
        "k": "normal"
      },
      {
        "t": 117650,
        "d": 5,
        "l": 0,
        "k": "normal"
      },
      {
        "t": 117650,
        "d": 2,
        "l": 0,
        "k": "normal"
      },
      {
        "t": 117650,
        "d": 3,
        "l": 0,
        "k": "normal"
      },
      {
        "t": 117828.571428572,
        "d": 6,
        "l": 0,
        "k": "normal"
      },
      {
        "t": 117828.571428572,
        "d": 3,
        "l": 0,
        "k": "normal"
      },
      {
        "t": 118007.142857143,
        "d": 5,
        "l": 0,
        "k": "normal"
      },
      {
        "t": 118007.142857143,
        "d": 0,
        "l": 625,
        "k": "normal"
      },
      {
        "t": 118007.142857143,
        "d": 7,
        "l": 0,
        "k": "normal"
      },
      {
        "t": 118185.714285714,
        "d": 4,
        "l": 0,
        "k": "normal"
      },
      {
        "t": 118185.714285714,
        "d": 7,
        "l": 0,
        "k": "normal"
      },
      {
        "t": 118364.285714286,
        "d": 7,
        "l": 267.857142857143,
        "k": "normal"
      },
      {
        "t": 118721.428571429,
        "d": 3,
        "l": 0,
        "k": "normal"
      },
      {
        "t": 118900,
        "d": 0,
        "l": 0,
        "k": "normal"
      },
      {
        "t": 119078.571428572,
        "d": 1,
        "l": 0,
        "k": "normal"
      },
      {
        "t": 119257.142857143,
        "d": 2,
        "l": 0,
        "k": "normal"
      },
      {
        "t": 119435.714285714,
        "d": 1,
        "l": 0,
        "k": "normal"
      },
      {
        "t": 119435.714285714,
        "d": 3,
        "l": 0,
        "k": "normal"
      },
      {
        "t": 119614.285714286,
        "d": 0,
        "l": 0,
        "k": "normal"
      },
      {
        "t": 119614.285714286,
        "d": 3,
        "l": 0,
        "k": "normal"
      },
      {
        "t": 119792.857142857,
        "d": 3,
        "l": 267.857142857143,
        "k": "normal"
      },
      {
        "t": 120150,
        "d": 5,
        "l": 0,
        "k": "normal"
      },
      {
        "t": 120328.571428572,
        "d": 7,
        "l": 0,
        "k": "normal"
      },
      {
        "t": 120507.142857143,
        "d": 6,
        "l": 0,
        "k": "normal"
      },
      {
        "t": 120685.714285714,
        "d": 5,
        "l": 0,
        "k": "normal"
      },
      {
        "t": 120864.285714286,
        "d": 4,
        "l": 267.857142857143,
        "k": "normal"
      },
      {
        "t": 121221.428571429,
        "d": 7,
        "l": 625,
        "k": "normal"
      },
      {
        "t": 121578.571428572,
        "d": 1,
        "l": 0,
        "k": "normal"
      },
      {
        "t": 121757.142857143,
        "d": 3,
        "l": 0,
        "k": "normal"
      },
      {
        "t": 121935.714285714,
        "d": 4,
        "l": 267.857142857143,
        "k": "normal"
      },
      {
        "t": 121935.714285714,
        "d": 2,
        "l": 0,
        "k": "normal"
      },
      {
        "t": 122114.285714286,
        "d": 1,
        "l": 0,
        "k": "normal"
      },
      {
        "t": 122292.857142857,
        "d": 7,
        "l": 625,
        "k": "normal"
      },
      {
        "t": 122292.857142857,
        "d": 0,
        "l": 267.857142857143,
        "k": "normal"
      },
      {
        "t": 122650,
        "d": 3,
        "l": 267.857142857143,
        "k": "normal"
      },
      {
        "t": 123007.142857143,
        "d": 5,
        "l": 0,
        "k": "normal"
      },
      {
        "t": 123257.142857143,
        "d": 7,
        "l": 0,
        "k": "normal"
      },
      {
        "t": 123507.142857143,
        "d": 7,
        "l": 0,
        "k": "normal"
      },
      {
        "t": 123757.142857143,
        "d": 4,
        "l": 0,
        "k": "normal"
      },
      {
        "t": 123882.142857143,
        "d": 4,
        "l": 0,
        "k": "normal"
      },
      {
        "t": 124007.142857143,
        "d": 5,
        "l": 0,
        "k": "normal"
      },
      {
        "t": 124257.142857143,
        "d": 7,
        "l": 0,
        "k": "normal"
      },
      {
        "t": 124507.142857143,
        "d": 7,
        "l": 0,
        "k": "normal"
      },
      {
        "t": 124757.142857143,
        "d": 4,
        "l": 0,
        "k": "normal"
      },
      {
        "t": 125007.142857143,
        "d": 1,
        "l": 0,
        "k": "normal"
      },
      {
        "t": 125257.142857143,
        "d": 3,
        "l": 0,
        "k": "normal"
      },
      {
        "t": 125507.142857143,
        "d": 3,
        "l": 0,
        "k": "normal"
      },
      {
        "t": 125757.142857143,
        "d": 0,
        "l": 0,
        "k": "normal"
      },
      {
        "t": 125882.142857143,
        "d": 0,
        "l": 0,
        "k": "normal"
      },
      {
        "t": 126007.142857143,
        "d": 1,
        "l": 0,
        "k": "normal"
      },
      {
        "t": 126257.142857143,
        "d": 3,
        "l": 0,
        "k": "normal"
      },
      {
        "t": 126507.142857143,
        "d": 3,
        "l": 0,
        "k": "normal"
      },
      {
        "t": 126757.142857143,
        "d": 0,
        "l": 0,
        "k": "normal"
      },
      {
        "t": 127007.142857143,
        "d": 5,
        "l": 0,
        "k": "normal"
      },
      {
        "t": 127257.142857143,
        "d": 4,
        "l": 0,
        "k": "normal"
      },
      {
        "t": 127507.142857143,
        "d": 6,
        "l": 0,
        "k": "normal"
      },
      {
        "t": 127757.142857143,
        "d": 7,
        "l": 0,
        "k": "normal"
      },
      {
        "t": 128007.142857143,
        "d": 6,
        "l": 0,
        "k": "normal"
      },
      {
        "t": 128257.142857143,
        "d": 5,
        "l": 0,
        "k": "normal"
      },
      {
        "t": 128507.142857143,
        "d": 4,
        "l": 0,
        "k": "normal"
      },
      {
        "t": 128757.142857143,
        "d": 7,
        "l": 0,
        "k": "normal"
      },
      {
        "t": 129007.142857143,
        "d": 1,
        "l": 0,
        "k": "normal"
      },
      {
        "t": 129257.142857143,
        "d": 0,
        "l": 0,
        "k": "normal"
      },
      {
        "t": 129507.142857143,
        "d": 2,
        "l": 0,
        "k": "normal"
      },
      {
        "t": 129757.142857143,
        "d": 3,
        "l": 0,
        "k": "normal"
      },
      {
        "t": 130007.142857143,
        "d": 2,
        "l": 0,
        "k": "normal"
      },
      {
        "t": 130257.142857143,
        "d": 1,
        "l": 0,
        "k": "normal"
      },
      {
        "t": 130507.142857143,
        "d": 0,
        "l": 0,
        "k": "normal"
      },
      {
        "t": 130757.142857143,
        "d": 3,
        "l": 0,
        "k": "normal"
      },
      {
        "t": 131007.142857143,
        "d": 5,
        "l": 0,
        "k": "normal"
      },
      {
        "t": 131257.142857143,
        "d": 7,
        "l": 0,
        "k": "normal"
      },
      {
        "t": 131507.142857143,
        "d": 7,
        "l": 0,
        "k": "normal"
      },
      {
        "t": 131757.142857143,
        "d": 4,
        "l": 0,
        "k": "normal"
      },
      {
        "t": 132007.142857143,
        "d": 5,
        "l": 0,
        "k": "normal"
      },
      {
        "t": 132257.142857143,
        "d": 7,
        "l": 0,
        "k": "normal"
      },
      {
        "t": 132507.142857143,
        "d": 6,
        "l": 375,
        "k": "normal"
      },
      {
        "t": 133007.142857143,
        "d": 1,
        "l": 0,
        "k": "normal"
      },
      {
        "t": 133257.142857143,
        "d": 3,
        "l": 0,
        "k": "normal"
      },
      {
        "t": 133507.142857143,
        "d": 3,
        "l": 0,
        "k": "normal"
      },
      {
        "t": 133757.142857143,
        "d": 0,
        "l": 0,
        "k": "normal"
      },
      {
        "t": 134007.142857143,
        "d": 1,
        "l": 0,
        "k": "normal"
      },
      {
        "t": 134257.142857143,
        "d": 3,
        "l": 0,
        "k": "normal"
      },
      {
        "t": 134507.142857143,
        "d": 2,
        "l": 375,
        "k": "normal"
      },
      {
        "t": 135007.142857143,
        "d": 5,
        "l": 0,
        "k": "normal"
      },
      {
        "t": 135257.142857143,
        "d": 5,
        "l": 0,
        "k": "normal"
      },
      {
        "t": 135382.142857143,
        "d": 4,
        "l": 0,
        "k": "normal"
      },
      {
        "t": 135507.142857143,
        "d": 6,
        "l": 0,
        "k": "normal"
      },
      {
        "t": 135757.142857143,
        "d": 4,
        "l": 0,
        "k": "normal"
      },
      {
        "t": 135882.142857143,
        "d": 5,
        "l": 0,
        "k": "normal"
      },
      {
        "t": 136007.142857143,
        "d": 7,
        "l": 0,
        "k": "normal"
      },
      {
        "t": 136257.142857143,
        "d": 5,
        "l": 0,
        "k": "normal"
      },
      {
        "t": 136507.142857143,
        "d": 6,
        "l": 0,
        "k": "normal"
      },
      {
        "t": 136757.142857143,
        "d": 7,
        "l": 0,
        "k": "normal"
      },
      {
        "t": 137007.142857143,
        "d": 1,
        "l": 0,
        "k": "normal"
      },
      {
        "t": 137257.142857143,
        "d": 1,
        "l": 0,
        "k": "normal"
      },
      {
        "t": 137382.142857143,
        "d": 0,
        "l": 0,
        "k": "normal"
      },
      {
        "t": 137507.142857143,
        "d": 2,
        "l": 0,
        "k": "normal"
      },
      {
        "t": 137507.142857143,
        "d": 7,
        "l": 375,
        "k": "normal"
      },
      {
        "t": 137757.142857143,
        "d": 0,
        "l": 0,
        "k": "normal"
      },
      {
        "t": 137882.142857143,
        "d": 1,
        "l": 0,
        "k": "normal"
      },
      {
        "t": 138007.142857143,
        "d": 3,
        "l": 0,
        "k": "normal"
      },
      {
        "t": 138007.142857143,
        "d": 6,
        "l": 375,
        "k": "normal"
      },
      {
        "t": 138257.142857143,
        "d": 1,
        "l": 0,
        "k": "normal"
      },
      {
        "t": 138507.142857143,
        "d": 2,
        "l": 0,
        "k": "normal"
      },
      {
        "t": 138507.142857143,
        "d": 4,
        "l": 375,
        "k": "normal"
      },
      {
        "t": 138757.142857143,
        "d": 3,
        "l": 0,
        "k": "normal"
      },
      {
        "t": 139007.142857143,
        "d": 0,
        "l": 875,
        "k": "normal"
      },
      {
        "t": 139007.142857143,
        "d": 5,
        "l": 875,
        "k": "normal"
      }
    ],
    "normal": [    ]
  },
  "generatedBy": "Friday Night Funkin' - v0.4.1"
}